Metadata-Version: 2.1
Name: consolec
Version: 0.0.2
Summary: Python module for work in console | Two It 2022
Home-page: https://github.com/TwoIt202/Consolec
Download-URL: 
Author: two-it2022
Author-email: kodland.group@gmail.com
Classifier: Operating System :: OS Independent
Classifier: Intended Audience :: End Users/Desktop
Classifier: Intended Audience :: Developers
Classifier: Programming Language :: Python
Classifier: Programming Language :: Python :: 3.8
Classifier: Programming Language :: Python :: 3.9
Classifier: Programming Language :: Python :: 3.10
Classifier: Programming Language :: Python :: 3.11
